[
    {
        "question_id": "fc8bca7fc5d628ab821aabb0d9a99d74",
        "category": "Nezařazeno",
        "question_text": "Ultralehký vrtulníkk může přistávat a vzlétat z plochy vymezené v územněplánovací dokumentaci pro letecko chemickou činnost:",
        "options": {
            "option_a": "při splnění stanovených podmínek",
            "option_b": "kdykoliv",
            "option_c": "nesmí"
        },
        "correct_option": "A",
        "points": 0,
        "explanation": null,
        "occurrence_count": 1,
        "last_seen": "2024-07-22",
        "first_seen": "2024-07-22"
    },
    {
        "question_id": "f6018a9d0ac27dcb9d62a001e55703c5",
        "category": "Navigace a letové přístroje",
        "question_text": "9 cm na mapě 1 : 500 000 odpovídá ve skutečnosti:",
        "options": {
            "option_a": "50 km",
            "option_b": "45 km",
            "option_c": "60 km"
        },
        "correct_option": "B",
        "points": 0,
        "explanation": null,
        "occurrence_count": 1,
        "last_seen": "2024-07-22",
        "first_seen": "2024-07-22"
    },
    {
        "question_id": "f5ef4d3727bbd8a9f51be6d159e30872",
        "category": "Nezařazeno",
        "question_text": "Z hlediska bezpečnosti letu je u vrtulníku obecně nejdůležitější:",
        "options": {
            "option_a": "udržení otáček nosného rotoru v předepsaném rozmezí",
            "option_b": "udržení stanovených otáček motoru",
            "option_c": "udržení potřebné dopředné rychlosti"
        },
        "correct_option": "A",
        "points": 0,
        "explanation": null,
        "occurrence_count": 1,
        "last_seen": "2024-07-22",
        "first_seen": "2024-07-22"
    },
    {
        "question_id": "f2ff39d5f630b639b93d169137a7f42a",
        "category": "Všeobecné znalosti letadel",
        "question_text": "Prázdná hmotnost SLZ je:",
        "options": {
            "option_a": "hmotnost celého letadla s nákladem v okamžiku dotyku při přistání",
            "option_b": "hmotnost vystrojeného letadla bez posádky, bez přepravovaného nákladu, bez paliva, ale s náplněmi v motoru (olej, voda)",
            "option_c": "hmotnost úplně vystrojeného letadla i s přepravovaným nákladem, ale bez hmotnosti paliva (pohonných hmot)"
        },
        "correct_option": "B",
        "points": 3,
        "explanation": null,
        "occurrence_count": 1,
        "last_seen": "2024-07-22",
        "first_seen": "2024-07-22"
    },
    {
        "question_id": "f149b04ee23aab2e67546c5db8b4243b",
        "category": "Meteorologie",
        "question_text": "Čočkovité podlouhlé mraky:",
        "options": {
            "option_a": "znamenají, že fouká ve výšce silný vítr, tudíž může hrozit nárazovitost větru",
            "option_b": "se vyskytují hlavně v tropech, u nás se objeví jen zřídka na jaře při prudké změně teploty",
            "option_c": "hlavně v létě znamenají, že se blíží nebezpečný druh okluzní fronty"
        },
        "correct_option": "A",
        "points": 0,
        "explanation": null,
        "occurrence_count": 1,
        "last_seen": "2024-07-22",
        "first_seen": "2024-07-22"
    },
    {
        "question_id": "ec5d3c8bd0512935b02d9cf1fb53c245",
        "category": "Navigace a letové přístroje",
        "question_text": "Rozdíl mezi UTC a letním středoevropským (SELČ) časem je:",
        "options": {
            "option_a": "není žádný",
            "option_b": "2 hodiny",
            "option_c": "1 hodina"
        },
        "correct_option": "B",
        "points": 0,
        "explanation": null,
        "occurrence_count": 1,
        "last_seen": "2024-07-22",
        "first_seen": "2024-07-22"
    },
    {
        "question_id": "ebbcfd64f9bdec0225fd7733b2a193a4",
        "category": "Principy letu a aerodynamika",
        "question_text": "Vliv reakčního momentu vrtule se bude nejvýrazněji projevovat:",
        "options": {
            "option_a": "když letadlo poletí malou rychlostí a pilot náhle zvýší výkon motoru",
            "option_b": "když letadlo poletí malou rychlostí při stažené přípusti",
            "option_c": "v zatáčkách při přechodu do stoupání nebo klesání"
        },
        "correct_option": "A",
        "points": 3,
        "explanation": null,
        "occurrence_count": 1,
        "last_seen": "2024-07-22",
        "first_seen": "2024-07-22"
    },
    {
        "question_id": "eb6154d0debd7ef5de97d1c1247fe69c",
        "category": "Provozní postupy a bezpečnost",
        "question_text": "V případě přeplnění nádrže palivového systému přebytečným palivem, nesmí mít toto palivo možnost zatékat do konstrukce letadla:",
        "options": {
            "option_a": "nadbytečný požadavek u většiny paliv",
            "option_b": "nesmí",
            "option_c": "může"
        },
        "correct_option": "B",
        "points": 3,
        "explanation": null,
        "occurrence_count": 1,
        "last_seen": "2024-07-22",
        "first_seen": "2024-07-22"
    },
    {
        "question_id": "e8ad481d95198d572998fafc661f42e2",
        "category": "Principy letu a aerodynamika",
        "question_text": "Odtržením proudnic rozumíme:",
        "options": {
            "option_a": "skokový přechod od turbulentního proudění nad horní plochou křídla k absolutní laminaritě",
            "option_b": "proud vzduchu přestane sledovat tvar profilu",
            "option_c": "proudnice opustí profil, po tom co opíšou jeho tvar"
        },
        "correct_option": "B",
        "points": 0,
        "explanation": null,
        "occurrence_count": 1,
        "last_seen": "2024-07-22",
        "first_seen": "2024-07-22"
    },
    {
        "question_id": "e736f4da30b31bf49110e8952973841d",
        "category": "Meteorologie",
        "question_text": "Jev nazývaný turbulence je definován jako:",
        "options": {
            "option_a": "síly působící na letadlo v různých směrech a udělující tomuto letadlu různá přídavná zrychlení",
            "option_b": "síly, které působí na letadlo ve vertikálním směru",
            "option_c": "síly, které zvyšují rychlost letícího letadla"
        },
        "correct_option": "A",
        "points": 0,
        "explanation": null,
        "occurrence_count": 1,
        "last_seen": "2024-07-22",
        "first_seen": "2024-07-22"
    },
    {
        "question_id": "e495814497c83009f130a15c1358b196",
        "category": "Všeobecné znalosti letadel",
        "question_text": "Alternátor nebo dynamo v letadle slouží?",
        "options": {
            "option_a": "pro napájení palubní sítě a dobíjení akumulátoru",
            "option_b": "pro napájení ukazatele paliva",
            "option_c": "k osvětlení letadla za snížené viditelnosti"
        },
        "correct_option": "A",
        "points": 3,
        "explanation": null,
        "occurrence_count": 1,
        "last_seen": "2024-07-22",
        "first_seen": "2024-07-22"
    },
    {
        "question_id": "e3daf047ac913151b5cabf5eb566be6b",
        "category": "Navigace a letové přístroje",
        "question_text": "Traťová rychlost (TR) je:",
        "options": {
            "option_a": "rychlost vůči vzduchové hmotě",
            "option_b": "rychlost, kterou nám udává rychloměr",
            "option_c": "rychlost, kterou letadlo letí vůči zemi"
        },
        "correct_option": "C",
        "points": 3,
        "explanation": null,
        "occurrence_count": 1,
        "last_seen": "2024-07-22",
        "first_seen": "2024-07-22"
    },
    {
        "question_id": "e0b8595b5d572ede81e2b74619d9293a",
        "category": "Nezařazeno",
        "question_text": "Náhlé odlehčení , způsobené prudkým potlačením páky cykliky může vést k záporným násobkům g, které jsou pro vrtulník s dvoulistým rotorem s polotuhým zavěšením listů houpavého typu nebezpečné především:",
        "options": {
            "option_a": "z důvodů možného selhání palivové a olejové instalace, která není na tyto násobky uzpůsobena",
            "option_b": "z důvodu rapidního nárůstu sil v řízení",
            "option_c": "z důvodu možnosti nárazu hrany rotorové hlavy do hlavního hřídele a tím jeho přeražení a tudíž oddělení rotoru od vrtulníku"
        },
        "correct_option": "C",
        "points": 3,
        "explanation": null,
        "occurrence_count": 1,
        "last_seen": "2024-07-22",
        "first_seen": "2024-07-22"
    },
    {
        "question_id": "dd5faa477c5dcaeca5c0ab5964a2ab56",
        "category": "Principy letu a aerodynamika",
        "question_text": "S jakou vrtulí dosáhne letadlo největší zrychlení při vzletu?",
        "options": {
            "option_a": "zrychlení při rozjezdu nezávisí na úhlu nastavení vrtule ani na jejich otáčkách",
            "option_b": "s vrtulí s velkým úhlem nastavení",
            "option_c": "s vrtulí s malým úhlem nastavení"
        },
        "correct_option": "C",
        "points": 0,
        "explanation": null,
        "occurrence_count": 1,
        "last_seen": "2024-07-22",
        "first_seen": "2024-07-22"
    },
    {
        "question_id": "dd17e83157088a36c8939586ab98ca0c",
        "category": "Meteorologie",
        "question_text": "Co rozumíme v meteorologii pojmem bouřka:",
        "options": {
            "option_a": "nejvýraznější projev konvekce ve volné atmosféře",
            "option_b": "přírodní jev doprovázený intenzivními srážkami a elektrickými výboji",
            "option_c": "jev totožný s pojmem „studená fronta“"
        },
        "correct_option": "B",
        "points": 3,
        "explanation": null,
        "occurrence_count": 1,
        "last_seen": "2024-07-22",
        "first_seen": "2024-07-22"
    },
    {
        "question_id": "d4f6e4e5db5ddadf5b1ee50ba7677778",
        "category": "Letecké předpisy a legislativa",
        "question_text": "Je neprovedení údržby na letadle důvodem k dočasné ztrátě letové způsobilosti letadla?",
        "options": {
            "option_a": "ano",
            "option_b": "není to důvod k dočasné ztrátě letové způsobilosti",
            "option_c": "jen při neprovedení roční nebo vyšší prohlídky"
        },
        "correct_option": "A",
        "points": 3,
        "explanation": null,
        "occurrence_count": 1,
        "last_seen": "2024-07-22",
        "first_seen": "2024-07-22"
    },
    {
        "question_id": "cd48c4431adaa9556181d95c4e320469",
        "category": "Navigace a letové přístroje",
        "question_text": "Středovým poledníkem nultého časového pásma je:",
        "options": {
            "option_a": "poledník procházející severním zeměpisným pólem",
            "option_b": "poledník, procházející hvězdárnou v Greenwich v Anglii",
            "option_c": "poledník, procházející městem Oxford v Anglii"
        },
        "correct_option": "B",
        "points": 3,
        "explanation": null,
        "occurrence_count": 1,
        "last_seen": "2024-07-22",
        "first_seen": "2024-07-22"
    },
    {
        "question_id": "c6b63a147c09bbe2cad8fd7c75798080",
        "category": "Meteorologie",
        "question_text": "Jak se pohybují vzduchové hmoty na teplé frontě?",
        "options": {
            "option_a": "Teplý vzduch se nasunuje nad hmoty studeného vzduchu",
            "option_b": "Teplý vzduch se nasunuje pod hmoty studeného vzduchu",
            "option_c": "Studený vzduch se nasunuje nad hmoty teplého vzduchu"
        },
        "correct_option": "A",
        "points": 3,
        "explanation": null,
        "occurrence_count": 1,
        "last_seen": "2024-07-22",
        "first_seen": "2024-07-22"
    },
    {
        "question_id": "c54260aeb015c91dda3c0d113dbc31a6",
        "category": "Principy letu a aerodynamika",
        "question_text": "Vztlak vzniká při obtékání profilu v důsledku vytvoření rozdílu tlaků nad a pod profilem. Jaký tlak je pod a nad profilem a jaký je při běžných úhlech náběhu poměr jejich velikostí?",
        "options": {
            "option_a": "pod profilem vzniká přetlak, nad profilem podtlak, jejichž velikosti jsou stejné",
            "option_b": "pod profilem vzniká podtlak, nad profilem přetlak, který je asi třikrát větší, než podtlak",
            "option_c": "pod profilem vzniká přetlak , nad profilem podtlak, ve vzájemném poměru je 1/3 přetlaku a 2/3 podtlaku"
        },
        "correct_option": "C",
        "points": 0,
        "explanation": null,
        "occurrence_count": 1,
        "last_seen": "2024-07-22",
        "first_seen": "2024-07-22"
    },
    {
        "question_id": "c4c4af95427a1cefa0b58604d46a67e7",
        "category": "Meteorologie",
        "question_text": "Konvekční aktivita ve středních zeměpisných šířkách je největší:",
        "options": {
            "option_a": "v létě odpoledne",
            "option_b": "v poledne",
            "option_c": "v zimě v poledne"
        },
        "correct_option": "A",
        "points": 0,
        "explanation": null,
        "occurrence_count": 1,
        "last_seen": "2024-07-22",
        "first_seen": "2024-07-22"
    },
    {
        "question_id": "c341a3ef9b056be4a1c326bf0ff28468",
        "category": "Meteorologie",
        "question_text": "Srážkové pásmo teplé fronty je:",
        "options": {
            "option_a": "převážně těsně za čarou fronty a jedná se o srážky občasné",
            "option_b": "před čarou fronty a jde o srážky trvalé",
            "option_c": "na čáře fronty a jde o srážky krátkodobého charakteru"
        },
        "correct_option": "B",
        "points": 0,
        "explanation": null,
        "occurrence_count": 1,
        "last_seen": "2024-07-22",
        "first_seen": "2024-07-22"
    },
    {
        "question_id": "bb5387a2dfefcaf8ba4ad9ffe79f3336",
        "category": "Letové výkony a plánování",
        "question_text": "Během letu zjistíte, že cílového letiště dosáhnete za 45 minut, zbytek LPH 10 l, průměrná spotřeba činí 15 l/h. Doletíte bez doplnění LPH na cílové letiště ?",
        "options": {
            "option_a": "ne",
            "option_b": "ano",
            "option_c": "ano, ale nezbude žádná rezerva paliva"
        },
        "correct_option": "A",
        "points": 3,
        "explanation": null,
        "occurrence_count": 1,
        "last_seen": "2024-07-22",
        "first_seen": "2024-07-22"
    },
    {
        "question_id": "bb1a1e4ebfb8e414640770581fe5b85c",
        "category": "Navigace a letové přístroje",
        "question_text": "10 cm na mapě 1 : 200 000 odpovídá ve skutečnosti:",
        "options": {
            "option_a": "50 km",
            "option_b": "200 km",
            "option_c": "20 km"
        },
        "correct_option": "C",
        "points": 3,
        "explanation": null,
        "occurrence_count": 1,
        "last_seen": "2024-07-22",
        "first_seen": "2024-07-22"
    },
    {
        "question_id": "b6c4dc41540fb9af08919fb48d9d980e",
        "category": "Všeobecné znalosti letadel",
        "question_text": "Reduktor slouží (mimo jiné)?",
        "options": {
            "option_a": "ke zvýšení otáček vrtule oproti motoru",
            "option_b": "ke snížení otáček vrtule oproti motoru",
            "option_c": "ke správnému nastavení listů vrtule a tím k jejímu správnému aerodynamickému vyvážení"
        },
        "correct_option": "B",
        "points": 3,
        "explanation": null,
        "occurrence_count": 1,
        "last_seen": "2024-07-22",
        "first_seen": "2024-07-22"
    },
    {
        "question_id": "af0dd5b3da22a19d7f71e3a2b919147f",
        "category": "Všeobecné znalosti letadel",
        "question_text": "Menší množství oleje, než minimální předepsané u čtyřdobého motoru:",
        "options": {
            "option_a": "je žádoucí pro snížení hmotnosti",
            "option_b": "může způsobit nedostatečné mazání a následnou poruchu motoru",
            "option_c": "snižuje tření v motoru a tím zvýší jeho výkon"
        },
        "correct_option": "B",
        "points": 3,
        "explanation": null,
        "occurrence_count": 1,
        "last_seen": "2024-07-22",
        "first_seen": "2024-07-22"
    },
    {
        "question_id": "ad48b7a482c98fb7e36942f55fe3d3c5",
        "category": "Principy letu a aerodynamika",
        "question_text": "Hustota vzduchu:",
        "options": {
            "option_a": "roste s rostoucí teplotou",
            "option_b": "snižuje se s klesající teplotou",
            "option_c": "roste s klesající teplotou vzduchu"
        },
        "correct_option": "C",
        "points": 0,
        "explanation": null,
        "occurrence_count": 1,
        "last_seen": "2024-07-22",
        "first_seen": "2024-07-22"
    },
    {
        "question_id": "aa088ac63982efda7563be293ff9773f",
        "category": "Navigace a letové přístroje",
        "question_text": "Letíme kursem 030°, točíme pravou zatáčku o náklonu 15 st. Na jakém kursu musíme srovnat zatáčku, abychom letěli kursem 180 stupňů?",
        "options": {
            "option_a": "na 210°",
            "option_b": "na 180°",
            "option_c": "na 150°"
        },
        "correct_option": "A",
        "points": 0,
        "explanation": null,
        "occurrence_count": 1,
        "last_seen": "2024-07-22",
        "first_seen": "2024-07-22"
    },
    {
        "question_id": "a9ff4b4913c85a36c3becdb3cb2344d7",
        "category": "Navigace a letové přístroje",
        "question_text": "Při provádění srovnávací orientace je vždy spolehlivější:",
        "options": {
            "option_a": "soustředit pozornost na jeden orientační bod",
            "option_b": "vyhledat a určit několik orientačních bodů",
            "option_c": "pozorně prohlížet terén pod letadlem"
        },
        "correct_option": "B",
        "points": 3,
        "explanation": null,
        "occurrence_count": 1,
        "last_seen": "2024-07-22",
        "first_seen": "2024-07-22"
    },
    {
        "question_id": "a7a8cb642633240afa1d318ed3ca2482",
        "category": "Meteorologie",
        "question_text": "Přízemní projevy aktivní bouřky nebezpečné pro letecký provoz:",
        "options": {
            "option_a": "húlava na čele bouřky, existence silného vzestupného proudu před húlavou, silný sestupný proud za húlavou v oblasti vypadávajících srážek, silné nárazy větru",
            "option_b": "vypadávání trvalých srážek",
            "option_c": "snížení základny oblačnosti, snižování dohlednosti"
        },
        "correct_option": "A",
        "points": 0,
        "explanation": null,
        "occurrence_count": 1,
        "last_seen": "2024-07-22",
        "first_seen": "2024-07-22"
    },
    {
        "question_id": "a707693ea900857a71f92209ceb428bc",
        "category": "Letecké předpisy a legislativa",
        "question_text": "Do zakázaného prostoru (LK P) pilot:",
        "options": {
            "option_a": "může vletět, nesmí jej však opustit",
            "option_b": "nesmí vletět pokud příslušný úřad nevydá zvláštní povolení",
            "option_c": "může vletět v rámci prostoru třídy G a E avšak nejvýše rychlostí 460 km/hod IAS"
        },
        "correct_option": "B",
        "points": 3,
        "explanation": null,
        "occurrence_count": 1,
        "last_seen": "2024-07-22",
        "first_seen": "2024-07-22"
    },
    {
        "question_id": "a656e36b423dc8714d63840498fb5aa2",
        "category": "Provozní postupy a bezpečnost",
        "question_text": "Každá závada (porucha) mající vliv na letovou způsobilost, která byla zjištěna na letadle, jeho výstroji a pohonné jednotce musí být odstraněna před zahájením dalšího letu:",
        "options": {
            "option_a": "nemusí být odstraněna před zahájením letištního letu",
            "option_b": "ano – musí být odstraněna před zahájením dalšího letu",
            "option_c": "musí být odstraněna pouze při provozu ve středisku pilotního výcviku"
        },
        "correct_option": "B",
        "points": 3,
        "explanation": null,
        "occurrence_count": 1,
        "last_seen": "2024-07-22",
        "first_seen": "2024-07-22"
    },
    {
        "question_id": "a522d3b1f34856ffd0c774cebeaca42b",
        "category": "Všeobecné znalosti letadel",
        "question_text": "Karburátor mimo jiné slouží:",
        "options": {
            "option_a": "k výrobě elektrické energie nutné pro napájení palubní sítě a dobíjení baterie",
            "option_b": "k omezení otáček aby na motoru nebyly překročeny maximální provozní otáčky",
            "option_c": "k vytvoření směsi paliva se vzduchem v nastaveném poměru a regulaci jejího množství do motoru"
        },
        "correct_option": "C",
        "points": 3,
        "explanation": null,
        "occurrence_count": 1,
        "last_seen": "2024-07-22",
        "first_seen": "2024-07-22"
    },
    {
        "question_id": "a27696dc9f0ad995b6cc58c4c25caf27",
        "category": "Nezařazeno",
        "question_text": "Správná technika odpoutání vrtulníku od země je:",
        "options": {
            "option_a": "prudké zvýšení úhlu nastavení listů rotoru pákou kolektivu při pracovních otáčkách s následným výskokem vrtulníku do bezpečné výšky a případným dorovnáním odchylek od správné polohy",
            "option_b": "Při volnoběžných otáčkách pilot nastaví pákou kolektivu předpokládaný úhel nastavení listů pro vis a následně zvětšováním otáček převede vrtulník do visu.Při tom odstraňuje tendence k posouvání, klonění či klopení a k pootáčení",
            "option_c": "pomalé zvyšování úhlu nastavení listů pákou kolektivu.Při tendenci vrtulníku posouvat se, klonit či klopit, nebo pootáčet se, pilot přeruší zvedání kolektivu a příslušným prvkem řízení odstraní zjištěnou tendenci. Tuto techniku v případě potřeby opakuje až do úplného odpoutání vrtulníku"
        },
        "correct_option": "C",
        "points": 3,
        "explanation": null,
        "occurrence_count": 1,
        "last_seen": "2024-07-22",
        "first_seen": "2024-07-22"
    },
    {
        "question_id": "a1008ae9ac84ef48672923944c3ea893",
        "category": "Navigace a letové přístroje",
        "question_text": "Jak mají být barevně označeny přístroje?",
        "options": {
            "option_a": "žádné hodnoty pro bezpečný provoz nemusí být označeny červenou radiální čárou",
            "option_b": "všechny maximální a pokud jsou dány i minimální hodnoty pro bezpečný provoz musí být označeny červenou radiální čárou",
            "option_c": "jen všechny maximální hodnoty pro bezpečný provoz musí být označeny červenou radiální čárou"
        },
        "correct_option": "B",
        "points": 3,
        "explanation": null,
        "occurrence_count": 1,
        "last_seen": "2024-07-22",
        "first_seen": "2024-07-22"
    },
    {
        "question_id": "9c35ac64a0f6617a3eeadc73d4bf86ca",
        "category": "Letecké předpisy a legislativa",
        "question_text": "Letí-li dvě letadla na protínajících se tratích v přibližně stejné hladině, musí se letadlo, které má po své pravé straně jiné letadlo vyhnout, vyjma tyto případy:",
        "options": {
            "option_a": "dopravní letadla mají přednost před jiným provozem",
            "option_b": "dispečer AFIS vydá řídící pokyn, kterým určí přednosti",
            "option_c": "motorové letadlo se musí vyhnout vzducholodím, kluzákům a balonům a jiným motorovým lletounům nebo SLZ, které mají ve vleku jiná letadla nebo předměty"
        },
        "correct_option": "C",
        "points": 0,
        "explanation": null,
        "occurrence_count": 1,
        "last_seen": "2024-07-22",
        "first_seen": "2024-07-22"
    },
    {
        "question_id": "9aec6467d6afece245b95d5bf64dd182",
        "category": "Provozní postupy a bezpečnost",
        "question_text": "Čtyři oranžové obdélníkové plochy sestavené do tvaru kříže s prázdným čtvercem uprostřed znamenají, že na letišti:",
        "options": {
            "option_a": "se provádí školní a výcvikové lety",
            "option_b": "je provoz kluzáků",
            "option_c": "se provádějí výsadky"
        },
        "correct_option": "C",
        "points": 3,
        "explanation": null,
        "occurrence_count": 1,
        "last_seen": "2024-07-22",
        "first_seen": "2024-07-22"
    },
    {
        "question_id": "9aa9bf7f263cda19a51856336026b417",
        "category": "Navigace a letové přístroje",
        "question_text": "Osa zemská je myšlená přímka středem země kolmá na rovník. Místa, kde protíná povrch země se nazývají póly (točny). Jsou to póly:",
        "options": {
            "option_a": "zeměpisné",
            "option_b": "totožné",
            "option_c": "magnetické"
        },
        "correct_option": "A",
        "points": 0,
        "explanation": null,
        "occurrence_count": 1,
        "last_seen": "2024-07-22",
        "first_seen": "2024-07-22"
    },
    {
        "question_id": "9a7408d2439cb6562b50c09058807435",
        "category": "Meteorologie",
        "question_text": "Nejspodnější vrstvu atmosféry nazýváme:",
        "options": {
            "option_a": "mezosféra",
            "option_b": "stratosféra",
            "option_c": "troposféra"
        },
        "correct_option": "C",
        "points": 3,
        "explanation": null,
        "occurrence_count": 1,
        "last_seen": "2024-07-22",
        "first_seen": "2024-07-22"
    },
    {
        "question_id": "93c1ac02b992c819a08869e9287aa828",
        "category": "Meteorologie",
        "question_text": "Vzduchovou hmotou nazýváme instabilní, pokud v ní dochází k:",
        "options": {
            "option_a": "konvektivním vertikálním pohybům",
            "option_b": "inverzím",
            "option_c": "tvorbě vrstevnaté oblačnosti"
        },
        "correct_option": "A",
        "points": 0,
        "explanation": null,
        "occurrence_count": 1,
        "last_seen": "2024-07-22",
        "first_seen": "2024-07-22"
    },
    {
        "question_id": "92b8d6852adc15be62958e940e0bb79c",
        "category": "Letecké předpisy a legislativa",
        "question_text": "Jaká je maximální vzletová hmotnost u jednomístného SLZ bez integrovaného záchranného systému:",
        "options": {
            "option_a": "280 kg",
            "option_b": "450 kg",
            "option_c": "300 kg"
        },
        "correct_option": "C",
        "points": 3,
        "explanation": null,
        "occurrence_count": 1,
        "last_seen": "2024-07-22",
        "first_seen": "2024-07-22"
    },
    {
        "question_id": "90e90f82cb91aa8c60333a090a2258cb",
        "category": "Navigace a letové přístroje",
        "question_text": "Barometrický výškoměr pracuje na základě",
        "options": {
            "option_a": "změny dynamického tlaku s výškou",
            "option_b": "změny statického tlaku s výškou",
            "option_c": "změny celkového tlaku s výškou"
        },
        "correct_option": "B",
        "points": 3,
        "explanation": null,
        "occurrence_count": 1,
        "last_seen": "2024-07-22",
        "first_seen": "2024-07-22"
    },
    {
        "question_id": "8d5c0c015870737eb4bfe23c5d2e4ee0",
        "category": "Provozní postupy a bezpečnost",
        "question_text": "Přejde-li letadlo s pevnou vrtulí do klesání bez ubrání přípusti motoru potom:",
        "options": {
            "option_a": "může zamrznout karburátor",
            "option_b": "se zvyšuje rychlost letu, ale ne otáčky",
            "option_c": "mohou být velmi snadno překročeny max. přípustné otáčky vrtule"
        },
        "correct_option": "C",
        "points": 3,
        "explanation": null,
        "occurrence_count": 1,
        "last_seen": "2024-07-22",
        "first_seen": "2024-07-22"
    },
    {
        "question_id": "8cb40d4171c28a4e22c53b476c884d03",
        "category": "Principy letu a aerodynamika",
        "question_text": "Pohyb letadla, při kterém se otáčí kolem své podélné osy se nazývá:",
        "options": {
            "option_a": "klopení",
            "option_b": "zatáčení",
            "option_c": "klonění"
        },
        "correct_option": "C",
        "points": 0,
        "explanation": null,
        "occurrence_count": 1,
        "last_seen": "2024-07-22",
        "first_seen": "2024-07-22"
    },
    {
        "question_id": "86ea51e10b63937656c7f1b5bc805308",
        "category": "Principy letu a aerodynamika",
        "question_text": "Zatížení letadla za letu může být:",
        "options": {
            "option_a": "pouze statické",
            "option_b": "statické a dynamické",
            "option_c": "pouze dynamické"
        },
        "correct_option": "B",
        "points": 3,
        "explanation": null,
        "occurrence_count": 1,
        "last_seen": "2024-07-22",
        "first_seen": "2024-07-22"
    },
    {
        "question_id": "8193748897c7dd02ce82268e6ed56cda",
        "category": "Nezařazeno",
        "question_text": "Při roztáčení rotoru před startem musí být páka kolektivu:",
        "options": {
            "option_a": "na horním dorazu",
            "option_b": "v poloze předpokládaného úhlu nastavení listů pro vis",
            "option_c": "na spodním dorazu"
        },
        "correct_option": "C",
        "points": 3,
        "explanation": null,
        "occurrence_count": 1,
        "last_seen": "2024-07-22",
        "first_seen": "2024-07-22"
    },
    {
        "question_id": "7cb6a21f32fe8463e1f1aabe8e399058",
        "category": "Nezařazeno",
        "question_text": "Při otáčení listu pracující vrtule vznikají na každém jeho profilu dvě síly, které jsou příčinou vzniku tahu a kroutícího momentu vrtule. Jak se tyto dvě síly nazývají?",
        "options": {
            "option_a": "odstředivá a dostředivá síla",
            "option_b": "vztlak a odpor",
            "option_c": "odstředivá síla a vztlak"
        },
        "correct_option": "B",
        "points": 0,
        "explanation": null,
        "occurrence_count": 1,
        "last_seen": "2024-07-22",
        "first_seen": "2024-07-22"
    },
    {
        "question_id": "79a740c2f2d4ffe5f7efb4484bbab2ad",
        "category": "Komunikace a letištní provoz",
        "question_text": "Letištní provoz je:",
        "options": {
            "option_a": "všechna letadla za letu nebo pohybující se na provozní ploše",
            "option_b": "provoz vozidel a osob na provozní ploše letiště",
            "option_c": "veškerý provoz na provozní ploše letiště a všechna letadla letící v blízkosti letiště"
        },
        "correct_option": "C",
        "points": 0,
        "explanation": null,
        "occurrence_count": 1,
        "last_seen": "2024-07-22",
        "first_seen": "2024-07-22"
    },
    {
        "question_id": "79848eb29beeb04c03f787556412dff5",
        "category": "Navigace a letové přístroje",
        "question_text": "Poloha zeměpisného a magnetického pólu:",
        "options": {
            "option_a": "magnetický pól je vždy na východ od zeměpisného",
            "option_b": "totožná",
            "option_c": "není shodná"
        },
        "correct_option": "C",
        "points": 0,
        "explanation": null,
        "occurrence_count": 1,
        "last_seen": "2024-07-22",
        "first_seen": "2024-07-22"
    },
    {
        "question_id": "76d81f3cce038eb366da11d74184dff1",
        "category": "Navigace a letové přístroje",
        "question_text": "225 stupňů je vedlejší světová strana:",
        "options": {
            "option_a": "jihozápad",
            "option_b": "severozápad",
            "option_c": "jihovýchod"
        },
        "correct_option": "A",
        "points": 0,
        "explanation": null,
        "occurrence_count": 1,
        "last_seen": "2024-07-22",
        "first_seen": "2024-07-22"
    },
    {
        "question_id": "7667ce076494822c32f2c2b7fa0946d9",
        "category": "Principy letu a aerodynamika",
        "question_text": "Při zvětšování úhlu náběhu:",
        "options": {
            "option_a": "klesá součinitel vztlaku a odporu",
            "option_b": "roste součinitel vztlaku, součinitel odporu klesá",
            "option_c": "roste součinitel vztlaku a odporu"
        },
        "correct_option": "C",
        "points": 3,
        "explanation": null,
        "occurrence_count": 1,
        "last_seen": "2024-07-22",
        "first_seen": "2024-07-22"
    },
    {
        "question_id": "74ff18ad99860fc48cb39329a106c458",
        "category": "Provozní postupy a bezpečnost",
        "question_text": "Výrobcem letadel jsou udávány výkony, obsluha a provozní rozsah centráží příslušného typu letadla. Tyto údaje je možné najít v:",
        "options": {
            "option_a": "letové příručce",
            "option_b": "palubním deníku",
            "option_c": "provozním bulletinu"
        },
        "correct_option": "A",
        "points": 3,
        "explanation": null,
        "occurrence_count": 1,
        "last_seen": "2024-07-22",
        "first_seen": "2024-07-22"
    },
    {
        "question_id": "730dc9d3fffac1b3aa2ff77f1037da8f",
        "category": "Nezařazeno",
        "question_text": "Reakční moment motorem poháněného rotoru způsobuje:",
        "options": {
            "option_a": "tendenci vrtulníku zatáčet na opačnou stranu, než se otáčí nosný rotor",
            "option_b": "tendenci vrtulníku klonit se na ustupující stranu rotoru",
            "option_c": "nutnost používání hrubších výchylek řídící páky, než u letounů"
        },
        "correct_option": "A",
        "points": 0,
        "explanation": null,
        "occurrence_count": 1,
        "last_seen": "2024-07-22",
        "first_seen": "2024-07-22"
    },
    {
        "question_id": "70f949ab900080ab62c156739a3fe719",
        "category": "Principy letu a aerodynamika",
        "question_text": "Jak se změní rychlost proudění a statický tlak v něm, když v nějakém místě dojde ke zhuštění proudnic?",
        "options": {
            "option_a": "rychlost se zvýší, statický tlak se zvýší",
            "option_b": "rychlost klesne, statický tlak klesne",
            "option_c": "rychlost se zvýší, statický tlak klesne"
        },
        "correct_option": "C",
        "points": 0,
        "explanation": null,
        "occurrence_count": 1,
        "last_seen": "2024-07-22",
        "first_seen": "2024-07-22"
    },
    {
        "question_id": "5eb54b92bc63fbeb8b51038fa70de78a",
        "category": "Nezařazeno",
        "question_text": "Režim autorotace vrtulníku znamená, že:",
        "options": {
            "option_a": "rotor vrtulníku není poháněn a jeho otáčky neustále klesají",
            "option_b": "v důsledku prudkého přitažení páky cykliky a vyšlápnutí nožního řízení dojde k odtržení proudu na jedné polovině rotorového disku a vztlak působící na opačné polovině zakřiví trajektorii letu do tvaru akrobatického prvku zvaného kopaný výkrut",
            "option_c": "rotor vrtulníku je poháněn pouze aerodynamickými silami, které vznikají při jeho obtékání vzduchem"
        },
        "correct_option": "C",
        "points": 3,
        "explanation": null,
        "occurrence_count": 1,
        "last_seen": "2024-07-22",
        "first_seen": "2024-07-22"
    },
    {
        "question_id": "5d06fb1923e9020c7ae76a593e661b0f",
        "category": "Letecké předpisy a legislativa",
        "question_text": "Musí být na palubě letadla při všech letech doklad o pojištění zákonné odpovědnosti?",
        "options": {
            "option_a": "ne při letištním letu",
            "option_b": "ne",
            "option_c": "ano"
        },
        "correct_option": "C",
        "points": 0,
        "explanation": null,
        "occurrence_count": 1,
        "last_seen": "2024-07-22",
        "first_seen": "2024-07-22"
    },
    {
        "question_id": "5a76c50d01e953f62def826c748285b8",
        "category": "Letecké předpisy a legislativa",
        "question_text": "Za stav SLZ před letem zodpovídá:",
        "options": {
            "option_a": "pilot",
            "option_b": "majitel",
            "option_c": "inspektor technik mající toto SLZ v evidenci"
        },
        "correct_option": "A",
        "points": 3,
        "explanation": null,
        "occurrence_count": 1,
        "last_seen": "2024-07-22",
        "first_seen": "2024-07-22"
    },
    {
        "question_id": "5563387268cd6aeaa9da4048161bc3ce",
        "category": "Meteorologie",
        "question_text": "Mezi oblačnost kupovitou patří:",
        "options": {
            "option_a": "As - altostratus",
            "option_b": "Cu - cumulus",
            "option_c": "St - stratus"
        },
        "correct_option": "B",
        "points": 3,
        "explanation": null,
        "occurrence_count": 1,
        "last_seen": "2024-07-22",
        "first_seen": "2024-07-22"
    },
    {
        "question_id": "551f6abfe786b6df104c9e727f0b1e1a",
        "category": "Navigace a letové přístroje",
        "question_text": "Výškoměr nastavený na hodnotu QFE letiště ukazuje po přistání na letišti:",
        "options": {
            "option_a": "nulovou výšku",
            "option_b": "nadmořskou výšku prahu VPD tohoto letiště",
            "option_c": "nadmořskou výšku vztažného bodu letiště"
        },
        "correct_option": "A",
        "points": 3,
        "explanation": null,
        "occurrence_count": 1,
        "last_seen": "2024-07-22",
        "first_seen": "2024-07-22"
    },
    {
        "question_id": "54a9e26b68fd5bf9fbbc172942a1e131",
        "category": "Letecké předpisy a legislativa",
        "question_text": "Sportovní létající zařízení může řídit",
        "options": {
            "option_a": "pilot, který je držitelem platného pilotního průkazu s příslušnou kvalifikací, nebo osoba oprávněná provozovatelem SLZ za přítomnosti pilota, pilotní žák za podmínek stanovených výcvikovou osnovou",
            "option_b": "pilot, který je držitelem platného posudku o zdravotní způsobilosti, nebo pilotní žák za podmínek stanovených výcvikovou osnovou",
            "option_c": "pilot, který je držitelem platného pilotního průkazu s příslušnou kvalifikací, nebo pilotní žák za podmínek stanovených výcvikovou osnovou"
        },
        "correct_option": "C",
        "points": 3,
        "explanation": null,
        "occurrence_count": 1,
        "last_seen": "2024-07-22",
        "first_seen": "2024-07-22"
    },
    {
        "question_id": "4e74a237dc2cde8cddaa51124064823a",
        "category": "Navigace a letové přístroje",
        "question_text": "Rozdíl mezi UTC a středoevropským (SEČ) časem je:",
        "options": {
            "option_a": "1 hodina",
            "option_b": "není žádný",
            "option_c": "2 hodiny"
        },
        "correct_option": "A",
        "points": 0,
        "explanation": null,
        "occurrence_count": 1,
        "last_seen": "2024-07-22",
        "first_seen": "2024-07-22"
    },
    {
        "question_id": "48855924d4e2c98b2f2c5e07bbf0d1d9",
        "category": "Meteorologie",
        "question_text": "Isobary jsou čáry na přízemních meteorologických mapách, které spojují místa:",
        "options": {
            "option_a": "se stejným tlakem přepočteným na hladinu moře",
            "option_b": "se stejnou vlhkostí",
            "option_c": "se stejnou teplotou přepočtenou na hladinu moře"
        },
        "correct_option": "A",
        "points": 3,
        "explanation": null,
        "occurrence_count": 1,
        "last_seen": "2024-07-22",
        "first_seen": "2024-07-22"
    },
    {
        "question_id": "46bc38b0844f3412ab13348913f6a7a1",
        "category": "Nezařazeno",
        "question_text": "Jaký účinek má vychýlení řídící páky doprava?",
        "options": {
            "option_a": "vrtulník se nakloní doprava, začne bočit doprava a v důsledku toho začne zatáčet doleva",
            "option_b": "vrtulník se nakloní doprava, začne bočit doleva a v důsledku toho začne zatáčet doprava",
            "option_c": "vrtulník se nakloní doprava, začne bočit doprava a v důsledku toho začne zatáčet doprava"
        },
        "correct_option": "C",
        "points": 3,
        "explanation": null,
        "occurrence_count": 1,
        "last_seen": "2024-07-22",
        "first_seen": "2024-07-22"
    },
    {
        "question_id": "4693a439bfd6e53d6a3bedac9fe53bc4",
        "category": "Letové výkony a plánování",
        "question_text": "Klouzavost vůči zemi se:",
        "options": {
            "option_a": "změní při změně hmotnosti",
            "option_b": "změní, fouká-li vítr",
            "option_c": "fouká-li vítr nezmění, protože efektivní nosná plocha zůstává stejná"
        },
        "correct_option": "B",
        "points": 0,
        "explanation": null,
        "occurrence_count": 1,
        "last_seen": "2024-07-22",
        "first_seen": "2024-07-22"
    },
    {
        "question_id": "439cd3ded3468b1adea33dec1fadb804",
        "category": "Provozní postupy a bezpečnost",
        "question_text": "Letadlo má v letové příručce a na štítku v kabině uvedenou max. vzletovou hmotnost 420 kg:",
        "options": {
            "option_a": "maximální vzletová hmotnost je 450 kg dle leteckého zákona.",
            "option_b": "pro vzlet musí být dodržena hmotnost 420 kg",
            "option_c": "pro vzlet musí být dodržena hmotnost 420 kg. Tato hmotnost může být překročena o hmotnost záchranného systému která se do max. vzletové hmotnosti nezapočitává."
        },
        "correct_option": "B",
        "points": 0,
        "explanation": null,
        "occurrence_count": 1,
        "last_seen": "2024-07-22",
        "first_seen": "2024-07-22"
    },
    {
        "question_id": "401cbe5c1050b97679d4c0fd7bc4b76d",
        "category": "Komunikace a letištní provoz",
        "question_text": "Je-li dáván příkaz letadlu na zemi orgánem letištní služby řízení světelným návěstím, potom stálé červené světlo znamená:",
        "options": {
            "option_a": "opusťte přistávací plochu",
            "option_b": "stůjte",
            "option_c": "vraťte se na místo odkud jste vyjel"
        },
        "correct_option": "B",
        "points": 3,
        "explanation": null,
        "occurrence_count": 1,
        "last_seen": "2024-07-22",
        "first_seen": "2024-07-22"
    },
    {
        "question_id": "351c238f453473647f178d4e6abd86d0",
        "category": "Letecké předpisy a legislativa",
        "question_text": "Maximální vzletová hmotnost letadla je:",
        "options": {
            "option_a": "největší hmotnost, při které letadlo vyhovuje technickým a zákonným omezením pro vzlet",
            "option_b": "největší hmotnost uvažovaná pro pojíždění letadla před vzletem",
            "option_c": "největší hmotnost naloženého letadla připraveného ke vzletu bez ohledu na omezení"
        },
        "correct_option": "A",
        "points": 3,
        "explanation": null,
        "occurrence_count": 1,
        "last_seen": "2024-07-22",
        "first_seen": "2024-07-22"
    },
    {
        "question_id": "315ded4113039b53b2719dda25e50e02",
        "category": "Navigace a letové přístroje",
        "question_text": "Dříve než v Praze vychází slunce:",
        "options": {
            "option_a": "v Moskvě",
            "option_b": "v Londýně",
            "option_c": "v Paříži"
        },
        "correct_option": "A",
        "points": 3,
        "explanation": null,
        "occurrence_count": 1,
        "last_seen": "2024-07-22",
        "first_seen": "2024-07-22"
    },
    {
        "question_id": "2c595cacb99af038a2a720827b88fb79",
        "category": "Principy letu a aerodynamika",
        "question_text": "Statické zatížení konstrukce letadla je definováno následovně:",
        "options": {
            "option_a": "je to zatížení, jehož velikost se s časem nemění nebo se mění poměrně pomalu (vliv jeho časového průběhu je zanedbatelný)",
            "option_b": "je to zatížení při dlouhodobém stání letadla na zemi",
            "option_c": "je to zatížení, jehož velikost se z časem mění náhle, nebo skokově"
        },
        "correct_option": "A",
        "points": 3,
        "explanation": null,
        "occurrence_count": 1,
        "last_seen": "2024-07-22",
        "first_seen": "2024-07-22"
    },
    {
        "question_id": "28f62567b379bdfabb91d8700acd3164",
        "category": "Provozní postupy a bezpečnost",
        "question_text": "Co znamená zkratka CTR?",
        "options": {
            "option_a": "koncová řízená oblast",
            "option_b": "prostor, kde není možné provádět lety VFR",
            "option_c": "řízený okrsek letiště"
        },
        "correct_option": "C",
        "points": 0,
        "explanation": null,
        "occurrence_count": 1,
        "last_seen": "2024-07-22",
        "first_seen": "2024-07-22"
    },
    {
        "question_id": "247376092f96b0e58a3f17aba6110800",
        "category": "Letecké předpisy a legislativa",
        "question_text": "UL letadla jsou dimenzovány na kladný provozní násobek:",
        "options": {
            "option_a": "+2 g",
            "option_b": "+4 g",
            "option_c": "+3 g"
        },
        "correct_option": "B",
        "points": 3,
        "explanation": null,
        "occurrence_count": 1,
        "last_seen": "2024-07-22",
        "first_seen": "2024-07-22"
    },
    {
        "question_id": "23b15ba0113570bceae1be52e6187b30",
        "category": "Navigace a letové přístroje",
        "question_text": "Nultý poledník je:",
        "options": {
            "option_a": "poledník neprocházející hvězdárnou v Greenwich, ovšem pouze na malé kružnici",
            "option_b": "poledník, zvaný též základní, procházející hvězdárnou v Greenwich v Anglii",
            "option_c": "poledník, na kterém se zeměpisná šířka i délka rovnají 0"
        },
        "correct_option": "B",
        "points": 3,
        "explanation": null,
        "occurrence_count": 1,
        "last_seen": "2024-07-22",
        "first_seen": "2024-07-22"
    },
    {
        "question_id": "21f2e2efd35bc052f68f6a515a609043",
        "category": "Nezařazeno",
        "question_text": "V letové příručce letadla je uvedena minimální hmotnost pilota 70 kg a maximální hmotnost pilota 110 kg. Pilot s hmotností 59 kg pro provedení letu provede:",
        "options": {
            "option_a": "let bez dalších úprav",
            "option_b": "dovážení své hmotnosti na 70 kg",
            "option_c": "dovážení své hmotnosti tak, aby na jeho sedačce byla hmotnost 110 kg."
        },
        "correct_option": "B",
        "points": 3,
        "explanation": null,
        "occurrence_count": 1,
        "last_seen": "2024-07-22",
        "first_seen": "2024-07-22"
    },
    {
        "question_id": "1f525d125cd310605213485ec22b9084",
        "category": "Letecké předpisy a legislativa",
        "question_text": "Spodní hranici řízeného okrsku (CTR) tvoří:",
        "options": {
            "option_a": "horní hranice třídy G",
            "option_b": "povrch země",
            "option_c": "stanovená výška nad mořem"
        },
        "correct_option": "B",
        "points": 0,
        "explanation": null,
        "occurrence_count": 1,
        "last_seen": "2024-07-22",
        "first_seen": "2024-07-22"
    },
    {
        "question_id": "167428f091d865e872b752165d079562",
        "category": "Letecké předpisy a legislativa",
        "question_text": "V letadle musí být umístěny předepsané štítky s provozním omezením. Tyto štítky musí být umístěny:",
        "options": {
            "option_a": "na libovolné pevné části konstrukce",
            "option_b": "na levém křídle ze spodu",
            "option_c": "v kabině letadla a v zorném poli pilota"
        },
        "correct_option": "C",
        "points": 3,
        "explanation": null,
        "occurrence_count": 1,
        "last_seen": "2024-07-22",
        "first_seen": "2024-07-22"
    },
    {
        "question_id": "1602f869f6a17889ffc771b61f2603b4",
        "category": "Navigace a letové přístroje",
        "question_text": "045 stupňů je vedlejší světová strana:",
        "options": {
            "option_a": "severovýchod",
            "option_b": "jihozápad",
            "option_c": "severozápad"
        },
        "correct_option": "A",
        "points": 3,
        "explanation": null,
        "occurrence_count": 1,
        "last_seen": "2024-07-22",
        "first_seen": "2024-07-22"
    },
    {
        "question_id": "0bfc7d95f7f2ee62b9b3d966ff3767b6",
        "category": "Letecké předpisy a legislativa",
        "question_text": "Přistávající letadlo má přednost před letadlem připraveným k odletu:",
        "options": {
            "option_a": "obvykle",
            "option_b": "pokud přistává a je v poslední fázi přiblížení na přistání",
            "option_c": "pokud je na okruhu s vysunutým podvozkem"
        },
        "correct_option": "B",
        "points": 3,
        "explanation": null,
        "occurrence_count": 1,
        "last_seen": "2024-07-22",
        "first_seen": "2024-07-22"
    },
    {
        "question_id": "07c88225924df9ee4516eb790eaca5a0",
        "category": "Principy letu a aerodynamika",
        "question_text": "Při kritickém úhlu náběhu:",
        "options": {
            "option_a": "dochází k prudkému nárůstu součinitele vztlaku",
            "option_b": "dosahuje součinitel vztlaku maximální hodnoty, při dalším zvyšování úhlu náběhu prudce klesá",
            "option_c": "dochází k náhlému poklesu součinitele odporu"
        },
        "correct_option": "B",
        "points": 3,
        "explanation": null,
        "occurrence_count": 1,
        "last_seen": "2024-07-22",
        "first_seen": "2024-07-22"
    },
    {
        "question_id": "05c974b9fd74517603f191cb39b96630",
        "category": "Provozní postupy a bezpečnost",
        "question_text": "Létat nad shromážděním osob v takové výšce, která by nedovolila v případě vzniklého nebezpečí přistát bez ohrožení pilota či osob na zemi je:",
        "options": {
            "option_a": "možné pouze na veřejném leteckém vystoupení s vydaným platným oprávněním",
            "option_b": "povoleno",
            "option_c": "zakázáno"
        },
        "correct_option": "C",
        "points": 0,
        "explanation": null,
        "occurrence_count": 1,
        "last_seen": "2024-07-22",
        "first_seen": "2024-07-22"
    },
    {
        "question_id": "037bdc4489de33b725d278c81612bb11",
        "category": "Navigace a letové přístroje",
        "question_text": "Pitot-statická sonda (pitotova trubice) snímá:",
        "options": {
            "option_a": "celkový tlak a statický tlak",
            "option_b": "dynamický tlak",
            "option_c": "statický tlak"
        },
        "correct_option": "A",
        "points": 3,
        "explanation": null,
        "occurrence_count": 1,
        "last_seen": "2024-07-22",
        "first_seen": "2024-07-22"
    },
    {
        "question_id": "021c9cc17f08a999e044a3327fa482f0",
        "category": "Nezařazeno",
        "question_text": "Podélné řízení vrtulníku:",
        "options": {
            "option_a": "je vybaveno dorazy, které však nemohu zabránit kontaktu rotoru s ocasním nosníkem, proto je nutno vyvarovat se velkých a prudkých přitažení podélného řízení",
            "option_b": "není vybaveno dorazy",
            "option_c": "je vybaveno dorazy, které brání kontaktu rotoru s ocasním nosníkem"
        },
        "correct_option": "A",
        "points": 0,
        "explanation": null,
        "occurrence_count": 1,
        "last_seen": "2024-07-22",
        "first_seen": "2024-07-22"
    }
]